sqs_mq.py
sqs_mq-0.2.1.dist-info/METADATA
sqs_mq-0.2.1.dist-info/RECORD
sqs_mq-0.2.1.dist-info/WHEEL
sqs_mq-0.2.1.dist-info/top_level.txt
