Metadata-Version: 2.1
Name: sqs-mq
Version: 0.2.1
Summary: A message queue system using AWS SQS
Home-page: https://github.com/mardix/sqs-mq
Author: Mardix
Author-email: mcx2082@gmail.com
License: MIT
Keywords: aws,sqs,mq,queue,amazon mq,celery,active mq,apollo,beanstalkd,resque,rabbitmq,gearman,ironmq,message
Platform: any
Classifier: Environment :: Web Environment
Classifier: Intended Audience :: Developers
Classifier: License :: OSI Approved :: BSD License
Classifier: Operating System :: OS Independent
Classifier: Programming Language :: Python
Classifier: Programming Language :: Python :: 2
Classifier: Programming Language :: Python :: 2.6
Classifier: Programming Language :: Python :: 2.7
Classifier: Programming Language :: Python :: 3
Classifier: Programming Language :: Python :: 3.3
Classifier: Programming Language :: Python :: 3.4
Classifier: Programming Language :: Python :: 3.5
Classifier: Topic :: Internet :: WWW/HTTP :: Dynamic Content
Classifier: Topic :: Software Development :: Libraries :: Python Modules
Requires-Dist: boto
Requires-Dist: python-slugify
